<annotation>
	<folder>OD set</folder>
	<filename>20201123_101507_023.jpg</filename>
	<path>C:\Users\Tom\Desktop\OD set\20201123_101507_023.jpg</path>
	<source>
		<database>Unknown</database>
	</source>
	<size>
		<width>240</width>
		<height>320</height>
		<depth>3</depth>
	</size>
	<segmented>0</segmented>
	<object>
		<name>2x2 green</name>
		<pose>Unspecified</pose>
		<truncated>0</truncated>
		<difficult>0</difficult>
		<bndbox>
			<xmin>143</xmin>
			<ymin>116</ymin>
			<xmax>188</xmax>
			<ymax>164</ymax>
		</bndbox>
	</object>
</annotation>
